drug2cell/__init__.py
drug2cell/chembl.py
drug2cell/cpdb_dict.pkl
drug2cell/data.py
drug2cell/drug-target_dicts.pkl
drug2cell/util.py
drug2cell-0.1.2.dist-info/LICENSE
drug2cell-0.1.2.dist-info/METADATA
drug2cell-0.1.2.dist-info/WHEEL
drug2cell-0.1.2.dist-info/top_level.txt
drug2cell-0.1.2.dist-info/RECORD
